README.rst
setup.py
mozls/__init__.py
mozls/__main__.py
mozls/cli.py
mozls/location.py
mozls/query.py
mozls/wireless.py
mozls.egg-info/PKG-INFO
mozls.egg-info/SOURCES.txt
mozls.egg-info/dependency_links.txt
mozls.egg-info/entry_points.txt
mozls.egg-info/requires.txt
mozls.egg-info/top_level.txt
mozls/test/__init__.py
mozls/test/test_cellular_query.py