Metadata-Version: 1.0
Name: mozls
Version: 0.0.1
Summary: Wrapper for the Mozilla Location Service API
Home-page: https://www.github.com/blocktrron/mozls
Author: David Bauer
Author-email: david@darmstadt.freifunk.net
License: AGPLv3
Platform: UNKNOWN
